README.md
setup.cfg
setup.py
unicatdb/__init__.py
unicatdb/client.py
unicatdb/configuration.py
unicatdb/servers.py
unicatdb.egg-info/PKG-INFO
unicatdb.egg-info/SOURCES.txt
unicatdb.egg-info/dependency_links.txt
unicatdb.egg-info/requires.txt
unicatdb.egg-info/top_level.txt
unicatdb/openapi_client/__init__.py
unicatdb/openapi_client/api_client.py
unicatdb/openapi_client/configuration.py
unicatdb/openapi_client/exceptions.py
unicatdb/openapi_client/recursive_urlencode.py
unicatdb/openapi_client/rest.py
unicatdb/openapi_client/api/__init__.py
unicatdb/openapi_client/api/attachments_api.py
unicatdb/openapi_client/api/charts_api.py
unicatdb/openapi_client/api/export_api.py
unicatdb/openapi_client/api/findings_api.py
unicatdb/openapi_client/api/schemas_api.py
unicatdb/openapi_client/api/security_api.py
unicatdb/openapi_client/api/tenants_api.py
unicatdb/openapi_client/models/__init__.py
unicatdb/openapi_client/models/attachment.py
unicatdb/openapi_client/models/attachment_array_response.py
unicatdb/openapi_client/models/attachment_fields_query.py
unicatdb/openapi_client/models/attachment_put_request.py
unicatdb/openapi_client/models/attachment_put_response.py
unicatdb/openapi_client/models/attachment_resource_object.py
unicatdb/openapi_client/models/attachment_resource_object_relationships.py
unicatdb/openapi_client/models/attachment_single_response.py
unicatdb/openapi_client/models/authentication_response.py
unicatdb/openapi_client/models/credentials_request_body.py
unicatdb/openapi_client/models/error_response.py
unicatdb/openapi_client/models/error_response_item.py
unicatdb/openapi_client/models/existing_finding_request_body.py
unicatdb/openapi_client/models/existing_finding_schema_request_body.py
unicatdb/openapi_client/models/existing_tenant_request_body.py
unicatdb/openapi_client/models/existing_tenant_user_request_body.py
unicatdb/openapi_client/models/finding.py
unicatdb/openapi_client/models/finding_array_response.py
unicatdb/openapi_client/models/finding_fields_query.py
unicatdb/openapi_client/models/finding_resource_object.py
unicatdb/openapi_client/models/finding_resource_object_relationships.py
