Metadata-Version: 2.1
Name: unicatdb
Version: 2.1
Summary: Python library for accessing API of the UniCatDB - Universal Catalog Database for biological findings.
Home-page: https://unicatdb.org
Author: Ondřej Doktor
Author-email: doktoo00@jcu.cz
License: All rights reserved
Keywords: UniCatDB,API,Universal Catalog Database
Platform: UNKNOWN
Classifier: Development Status :: 4 - Beta
Classifier: Intended Audience :: Science/Research
Classifier: Topic :: Software Development :: Build Tools
Classifier: License :: Other/Proprietary License
Classifier: Programming Language :: Python :: 3.7
